mt_aws_utils/__about__.py
mt_aws_utils/__init__.py
mt_aws_utils/apiutils.py
mt_aws_utils/awsutils.py
mt_aws_utils/dbutil.py
mt_aws_utils/mt_aws_utils-0.0.12-py3-none-any.whl
mt_aws_utils/mt_aws_utils-0.0.12.tar.gz
mt_aws_utils-0.0.13.dist-info/METADATA
mt_aws_utils-0.0.13.dist-info/WHEEL
mt_aws_utils-0.0.13.dist-info/licenses/LICENSE.txt
mt_aws_utils-0.0.13.dist-info/RECORD
