Metadata-Version: 2.1
Name: mt-aws-utils
Version: 0.0.13
Project-URL: Source, https://github.com/daddepledge/mt-aws-utils
Author-email: Sefton de Pledge <seftontycho@hotmail.co.uk>, John de Pledge <peaktuition@gmail.com>
License-File: LICENSE.txt
Requires-Python: >=3.8
Requires-Dist: lz4
Requires-Dist: pymysql
